tvm_valuetypes/__init__.py
tvm_valuetypes/cell.py
tvm_valuetypes/dict_utils.py
tvm_valuetypes/stack_utils.py
tvm_valuetypes-0.0.12.dist-info/LICENSE
tvm_valuetypes-0.0.12.dist-info/METADATA
tvm_valuetypes-0.0.12.dist-info/WHEEL
tvm_valuetypes-0.0.12.dist-info/top_level.txt
tvm_valuetypes-0.0.12.dist-info/RECORD
