Metadata-Version: 2.1
Name: tvm_valuetypes
Version: 0.0.12
Summary: Collection of utils for handling Telegram Open Network Virtual Machine value types
Home-page: https://github.com/EmelyanenkoK/tvm_valuetypes
Author: Emelyanenko Kirill
Author-email: emelyanenko.kirill@gmail.com
Classifier: Development Status :: 3 - Alpha
Classifier: Intended Audience :: Developers
Classifier: Programming Language :: Python :: 3
Classifier: License :: Other/Proprietary License
Classifier: Operating System :: OS Independent
Classifier: Topic :: Software Development :: Libraries
License-File: LICENSE
